{
    "info": {
        "name": "林尼",
        "description": "伶牙俐齿，演技精湛的著名枫丹魔术师，以精妙的手法和言语牵动着观众的心。",
        "rarity": "QUALITY_ORANGE",
        "weapon": "WEAPON_BOW",
        "birthday": "February 2nd",
        "element": "Pyro",
        "constellation": "黑斑猫座",
        "attributes": [
            {
                "level": 1,
                "ascension": 0,
                "hp": 858,
                "atk": 25,
                "def": 42,
                "CRIT Rate%": "0"
            },
            {
                "level": 2,
                "ascension": 0,
                "hp": 929,
                "atk": 27,
                "def": 45,
                "CRIT Rate%": "0"
            },
            {
                "level": 3,
                "ascension": 0,
                "hp": 1000,
                "atk": 29,
                "def": 49,
                "CRIT Rate%": "0"
            },
            {
                "level": 4,
                "ascension": 0,
                "hp": 1072,
                "atk": 31,
                "def": 52,
                "CRIT Rate%": "0"
            },
            {
                "level": 5,
                "ascension": 0,
                "hp": 1144,
                "atk": 33,
                "def": 56,
                "CRIT Rate%": "0"
            },
            {
                "level": 6,
                "ascension": 0,
                "hp": 1216,
                "atk": 35,
                "def": 59,
                "CRIT Rate%": "0"
            },
            {
                "level": 7,
                "ascension": 0,
                "hp": 1287,
                "atk": 37,
                "def": 63,
                "CRIT Rate%": "0"
            },
            {
                "level": 8,
                "ascension": 0,
                "hp": 1359,
                "atk": 39,
                "def": 66,
                "CRIT Rate%": "0"
            },
            {
                "level": 9,
                "ascension": 0,
                "hp": 1431,
                "atk": 41,
                "def": 70,
                "CRIT Rate%": "0"
            },
            {
                "level": 10,
                "ascension": 0,
                "hp": 1502,
                "atk": 43,
                "def": 73,
                "CRIT Rate%": "0"
            },
            {
                "level": 11,
                "ascension": 0,
                "hp": 1574,
                "atk": 45,
                "def": 77,
                "CRIT Rate%": "0"
            },
            {
                "level": 12,
                "ascension": 0,
                "hp": 1646,
                "atk": 48,
                "def": 80,
                "CRIT Rate%": "0"
            },
            {
                "level": 13,
                "ascension": 0,
                "hp": 1719,
                "atk": 50,
                "def": 84,
                "CRIT Rate%": "0"
            },
            {
                "level": 14,
                "ascension": 0,
                "hp": 1791,
                "atk": 52,
                "def": 87,
                "CRIT Rate%": "0"
            },
            {
                "level": 15,
                "ascension": 0,
                "hp": 1864,
                "atk": 54,
                "def": 91,
                "CRIT Rate%": "0"
            },
            {
                "level": 16,
                "ascension": 0,
                "hp": 1936,
                "atk": 56,
                "def": 94,
                "CRIT Rate%": "0"
            },
            {
                "level": 17,
                "ascension": 0,
                "hp": 2009,
                "atk": 58,
                "def": 98,
                "CRIT Rate%": "0"
            },
            {
                "level": 18,
                "ascension": 0,
                "hp": 2081,
                "atk": 60,
                "def": 102,
                "CRIT Rate%": "0"
            },
            {
                "level": 19,
                "ascension": 0,
                "hp": 2154,
                "atk": 62,
                "def": 105,
                "CRIT Rate%": "0"
            },
            {
                "level": 20,
                "ascension": 0,
                "hp": 2226,
                "atk": 64,
                "def": 109,
                "CRIT Rate%": "0"
            },
            {
                "level": 21,
                "ascension": 1,
                "hp": 3034,
                "atk": 88,
                "def": 148,
                "CRIT Rate%": "0"
            },
            {
                "level": 22,
                "ascension": 1,
                "hp": 3107,
                "atk": 90,
                "def": 152,
                "CRIT Rate%": "0"
            },
            {
                "level": 23,
                "ascension": 1,
                "hp": 3180,
                "atk": 92,
                "def": 155,
                "CRIT Rate%": "0"
            },
            {
                "level": 24,
                "ascension": 1,
                "hp": 3253,
                "atk": 94,
                "def": 159,
                "CRIT Rate%": "0"
            },
            {
                "level": 25,
                "ascension": 1,
                "hp": 3326,
                "atk": 96,
                "def": 162,
                "CRIT Rate%": "0"
            },
            {
                "level": 26,
                "ascension": 1,
                "hp": 3400,
                "atk": 98,
                "def": 166,
                "CRIT Rate%": "0"
            },
            {
                "level": 27,
                "ascension": 1,
                "hp": 3473,
                "atk": 100,
                "def": 170,
                "CRIT Rate%": "0"
            },
            {
                "level": 28,
                "ascension": 1,
                "hp": 3546,
                "atk": 102,
                "def": 173,
                "CRIT Rate%": "0"
            },
            {
                "level": 29,
                "ascension": 1,
                "hp": 3619,
                "atk": 104,
                "def": 177,
                "CRIT Rate%": "0"
            },
            {
                "level": 30,
                "ascension": 1,
                "hp": 3692,
                "atk": 107,
                "def": 180,
                "CRIT Rate%": "0"
            },
            {
                "level": 31,
                "ascension": 1,
                "hp": 3766,
                "atk": 109,
                "def": 184,
                "CRIT Rate%": "0"
            },
            {
                "level": 32,
                "ascension": 1,
                "hp": 3840,
                "atk": 111,
                "def": 187,
                "CRIT Rate%": "0"
            },
            {
                "level": 33,
                "ascension": 1,
                "hp": 3914,
                "atk": 113,
                "def": 191,
                "CRIT Rate%": "0"
            },
            {
                "level": 34,
                "ascension": 1,
                "hp": 3987,
                "atk": 115,
                "def": 195,
                "CRIT Rate%": "0"
            },
            {
                "level": 35,
                "ascension": 1,
                "hp": 4060,
                "atk": 117,
                "def": 198,
                "CRIT Rate%": "0"
            },
            {
                "level": 36,
                "ascension": 1,
                "hp": 4135,
                "atk": 119,
                "def": 202,
                "CRIT Rate%": "0"
            },
            {
                "level": 37,
                "ascension": 1,
                "hp": 4209,
                "atk": 121,
                "def": 205,
                "CRIT Rate%": "0"
            },
            {
                "level": 38,
                "ascension": 1,
                "hp": 4283,
                "atk": 124,
                "def": 209,
                "CRIT Rate%": "0"
            },
            {
                "level": 39,
                "ascension": 1,
                "hp": 4356,
                "atk": 126,
                "def": 213,
                "CRIT Rate%": "0"
            },
            {
                "level": 40,
                "ascension": 1,
                "hp": 4431,
                "atk": 128,
                "def": 216,
                "CRIT Rate%": "0"
            },
            {
                "level": 41,
                "ascension": 2,
                "hp": 5027,
                "atk": 145,
                "def": 245,
                "CRIT Rate%": "4.8"
            },
            {
                "level": 42,
                "ascension": 2,
                "hp": 5102,
                "atk": 147,
                "def": 249,
                "CRIT Rate%": "4.8"
            },
            {
                "level": 43,
                "ascension": 2,
                "hp": 5177,
                "atk": 149,
                "def": 253,
                "CRIT Rate%": "4.8"
            },
            {
                "level": 44,
                "ascension": 2,
                "hp": 5251,
                "atk": 152,
                "def": 256,
                "CRIT Rate%": "4.8"
            },
            {
                "level": 45,
                "ascension": 2,
                "hp": 5325,
                "atk": 154,
                "def": 260,
                "CRIT Rate%": "4.8"
            },
            {
                "level": 46,
                "ascension": 2,
                "hp": 5400,
                "atk": 156,
                "def": 264,
                "CRIT Rate%": "4.8"
            },
            {
                "level": 47,
                "ascension": 2,
                "hp": 5474,
                "atk": 158,
                "def": 267,
                "CRIT Rate%": "4.8"
            },
            {
                "level": 48,
                "ascension": 2,
                "hp": 5549,
                "atk": 160,
                "def": 271,
                "CRIT Rate%": "4.8"
            },
            {
                "level": 49,
                "ascension": 2,
                "hp": 5625,
                "atk": 162,
                "def": 275,
                "CRIT Rate%": "4.8"
            },
            {
                "level": 50,
                "ascension": 2,
                "hp": 5699,
                "atk": 164,
                "def": 278,
                "CRIT Rate%": "4.8"
            },
            {
                "level": 51,
                "ascension": 3,
                "hp": 6471,
                "atk": 187,
                "def": 316,
                "CRIT Rate%": "9.6"
            },
            {
                "level": 52,
                "ascension": 3,
                "hp": 6546,
                "atk": 189,
                "def": 320,
                "CRIT Rate%": "9.6"
            },
            {
                "level": 53,
                "ascension": 3,
                "hp": 6621,
                "atk": 191,
                "def": 323,
                "CRIT Rate%": "9.6"
            },
            {
                "level": 54,
                "ascension": 3,
                "hp": 6697,
                "atk": 193,
                "def": 327,
                "CRIT Rate%": "9.6"
            },
            {
                "level": 55,
                "ascension": 3,
                "hp": 6772,
                "atk": 195,
                "def": 331,
                "CRIT Rate%": "9.6"
            },
            {
                "level": 56,
                "ascension": 3,
                "hp": 6848,
                "atk": 198,
                "def": 334,
                "CRIT Rate%": "9.6"
            },
            {
                "level": 57,
                "ascension": 3,
                "hp": 6923,
                "atk": 200,
                "def": 338,
                "CRIT Rate%": "9.6"
            },
            {
                "level": 58,
                "ascension": 3,
                "hp": 6999,
                "atk": 202,
                "def": 342,
                "CRIT Rate%": "9.6"
            },
            {
                "level": 59,
                "ascension": 3,
                "hp": 7074,
                "atk": 204,
                "def": 345,
                "CRIT Rate%": "9.6"
            },
            {
                "level": 60,
                "ascension": 3,
                "hp": 7150,
                "atk": 206,
                "def": 349,
                "CRIT Rate%": "9.6"
            },
            {
                "level": 61,
                "ascension": 4,
                "hp": 7748,
                "atk": 224,
                "def": 378,
                "CRIT Rate%": "9.6"
            },
            {
                "level": 62,
                "ascension": 4,
                "hp": 7823,
                "atk": 226,
                "def": 382,
                "CRIT Rate%": "9.6"
            },
            {
                "level": 63,
                "ascension": 4,
                "hp": 7900,
                "atk": 228,
                "def": 386,
                "CRIT Rate%": "9.6"
            },
            {
                "level": 64,
                "ascension": 4,
                "hp": 7975,
                "atk": 230,
                "def": 389,
                "CRIT Rate%": "9.6"
            },
            {
                "level": 65,
                "ascension": 4,
                "hp": 8051,
                "atk": 232,
                "def": 393,
                "CRIT Rate%": "9.6"
            },
            {
                "level": 66,
                "ascension": 4,
                "hp": 8128,
                "atk": 235,
                "def": 397,
                "CRIT Rate%": "9.6"
            },
            {
                "level": 67,
                "ascension": 4,
                "hp": 8203,
                "atk": 237,
                "def": 400,
                "CRIT Rate%": "9.6"
            },
            {
                "level": 68,
                "ascension": 4,
                "hp": 8280,
                "atk": 239,
                "def": 404,
                "CRIT Rate%": "9.6"
            },
            {
                "level": 69,
                "ascension": 4,
                "hp": 8356,
                "atk": 241,
                "def": 408,
                "CRIT Rate%": "9.6"
            },
            {
                "level": 70,
                "ascension": 4,
                "hp": 8432,
                "atk": 243,
                "def": 412,
                "CRIT Rate%": "9.6"
            },
            {
                "level": 71,
                "ascension": 5,
                "hp": 9031,
                "atk": 261,
                "def": 441,
                "CRIT Rate%": "14.4"
            },
            {
                "level": 72,
                "ascension": 5,
                "hp": 9109,
                "atk": 263,
                "def": 445,
                "CRIT Rate%": "14.4"
            },
            {
                "level": 73,
                "ascension": 5,
                "hp": 9185,
                "atk": 265,
                "def": 448,
                "CRIT Rate%": "14.4"
            },
            {
                "level": 74,
                "ascension": 5,
                "hp": 9261,
                "atk": 267,
                "def": 452,
                "CRIT Rate%": "14.4"
            },
            {
                "level": 75,
                "ascension": 5,
                "hp": 9339,
                "atk": 270,
                "def": 456,
                "CRIT Rate%": "14.4"
            },
            {
                "level": 76,
                "ascension": 5,
                "hp": 9415,
                "atk": 272,
                "def": 460,
                "CRIT Rate%": "14.4"
            },
            {
                "level": 77,
                "ascension": 5,
                "hp": 9492,
                "atk": 274,
                "def": 463,
                "CRIT Rate%": "14.4"
            },
            {
                "level": 78,
                "ascension": 5,
                "hp": 9569,
                "atk": 276,
                "def": 467,
                "CRIT Rate%": "14.4"
            },
            {
                "level": 79,
                "ascension": 5,
                "hp": 9647,
                "atk": 278,
                "def": 471,
                "CRIT Rate%": "14.4"
            },
            {
                "level": 80,
                "ascension": 5,
                "hp": 9724,
                "atk": 281,
                "def": 475,
                "CRIT Rate%": "14.4"
            },
            {
                "level": 81,
                "ascension": 6,
                "hp": 10324,
                "atk": 298,
                "def": 504,
                "CRIT Rate%": "19.2"
            },
            {
                "level": 82,
                "ascension": 6,
                "hp": 10401,
                "atk": 300,
                "def": 508,
                "CRIT Rate%": "19.2"
            },
            {
                "level": 83,
                "ascension": 6,
                "hp": 10478,
                "atk": 302,
                "def": 511,
                "CRIT Rate%": "19.2"
            },
            {
                "level": 84,
                "ascension": 6,
                "hp": 10555,
                "atk": 305,
                "def": 515,
                "CRIT Rate%": "19.2"
            },
            {
                "level": 85,
                "ascension": 6,
                "hp": 10633,
                "atk": 307,
                "def": 519,
                "CRIT Rate%": "19.2"
            },
            {
                "level": 86,
                "ascension": 6,
                "hp": 10711,
                "atk": 309,
                "def": 523,
                "CRIT Rate%": "19.2"
            },
            {
                "level": 87,
                "ascension": 6,
                "hp": 10788,
                "atk": 311,
                "def": 527,
                "CRIT Rate%": "19.2"
            },
            {
                "level": 88,
                "ascension": 6,
                "hp": 10866,
                "atk": 314,
                "def": 530,
                "CRIT Rate%": "19.2"
            },
            {
                "level": 89,
                "ascension": 6,
                "hp": 10944,
                "atk": 316,
                "def": 534,
                "CRIT Rate%": "19.2"
            },
            {
                "level": 90,
                "ascension": 6,
                "hp": 11021,
                "atk": 318,
                "def": 538,
                "CRIT Rate%": "19.2"
            },
            {
                "level": 95,
                "ascension": 6,
                "hp": 11413,
                "atk": 354,
                "def": 557,
                "CRIT Rate%": "19.2"
            },
            {
                "level": 100,
                "ascension": 6,
                "hp": 11805,
                "atk": 390,
                "def": 576,
                "CRIT Rate%": "19.2"
            }
        ]
    },
    "icons": {
        "forward": "UI_AvatarIcon_Liney",
        "coop_img": "UI_CoopImg_Liney"
    },
    "ascension": {
        "202": 7049900,
        "exp": {
            "104001": 2,
            "104003": 418
        },
        "speciality": {
            "101236": 168
        },
        "elemental": {
            "104111": 1,
            "104112": 9,
            "104113": 9,
            "104114": 6
        },
        "worldmonster": {
            "112032": 18,
            "112033": 30,
            "112034": 36
        },
        "elitemonster": {
            "113051": 46
        }
    },
    "skills": {
        "normalattack": {
            "name": "迫牌易位式",
            "icon": "Skill_A_02",
            "multipliers": {
                "一段伤害": [
                    "38.79%",
                    "41.94%",
                    "45.1%",
                    "49.61%",
                    "52.77%",
                    "56.38%",
                    "61.34%",
                    "66.3%",
                    "71.26%",
                    "76.67%",
                    "82.08%",
                    "87.49%",
                    "92.91%",
                    "98.32%",
                    "103.73%"
                ],
                "二段伤害": [
                    "38.01%",
                    "41.11%",
                    "44.2%",
                    "48.62%",
                    "51.71%",
                    "55.25%",
                    "60.11%",
                    "64.97%",
                    "69.84%",
                    "75.14%",
                    "80.44%",
                    "85.75%",
                    "91.05%",
                    "96.36%",
                    "101.66%"
                ],
                "三段伤害": [
                    "27.26%+27.26%",
                    "29.48%+29.48%",
                    "31.7%+31.7%",
                    "34.87%+34.87%",
                    "37.09%+37.09%",
                    "39.63%+39.63%",
                    "43.11%+43.11%",
                    "46.6%+46.6%",
                    "50.09%+50.09%",
                    "53.89%+53.89%",
                    "57.69%+57.69%",
                    "61.5%+61.5%",
                    "65.3%+65.3%",
                    "69.11%+69.11%",
                    "72.91%+72.91%"
                ],
                "四段伤害": [
                    "56.93%",
                    "61.57%",
                    "66.2%",
                    "72.82%",
                    "77.45%",
                    "82.75%",
                    "90.03%",
                    "97.31%",
                    "104.6%",
                    "112.54%",
                    "120.48%",
                    "128.43%",
                    "136.37%",
                    "144.32%",
                    "152.26%"
                ],
                "下坠期间伤害": [
                    "56.83%",
                    "61.45%",
                    "66.08%",
                    "72.69%",
                    "77.31%",
                    "82.6%",
                    "89.87%",
                    "97.14%",
                    "104.41%",
                    "112.34%",
                    "120.27%",
                    "128.2%",
                    "136.12%",
                    "144.05%",
                    "151.98%"
                ],
                "低空/高空坠地冲击伤害": [
                    "113.63%/141.93%",
                    "122.88%/153.49%",
                    "132.13%/165.04%",
                    "145.35%/181.54%",
                    "154.59%/193.1%",
                    "165.16%/206.3%",
                    "179.7%/224.45%",
                    "194.23%/242.61%",
                    "208.77%/260.76%",
                    "224.62%/280.57%",
                    "240.48%/300.37%",
                    "256.34%/320.18%",
                    "272.19%/339.98%",
                    "288.05%/359.79%",
                    "303.9%/379.59%"
                ],
                "瞄准射击": [
                    "43.86%",
                    "47.43%",
                    "51%",
                    "56.1%",
                    "59.67%",
                    "63.75%",
                    "69.36%",
                    "74.97%",
                    "80.58%",
                    "86.7%",
                    "92.82%",
                    "98.94%",
                    "105.06%",
                    "111.18%",
                    "117.3%"
                ],
                "一段蓄力瞄准射击": [
                    "124%",
                    "133.3%",
                    "142.6%",
                    "155%",
                    "164.3%",
                    "173.6%",
                    "186%",
                    "198.4%",
                    "210.8%",
                    "223.2%",
                    "235.6%",
                    "248%",
                    "263.5%",
                    "279%",
                    "294.5%"
                ],
                "隐具魔术箭伤害": [
                    "172.8%",
                    "185.76%",
                    "198.72%",
                    "216%",
                    "228.96%",
                    "241.92%",
                    "259.2%",
                    "276.48%",
                    "293.76%",
                    "311.04%",
                    "328.32%",
                    "345.6%",
                    "367.2%",
                    "388.8%",
                    "410.4%"
                ],
                "生命值消耗": [
                    "20%生命值上限",
                    "20%生命值上限",
                    "20%生命值上限",
                    "20%生命值上限",
                    "20%生命值上限",
                    "20%生命值上限",
                    "20%生命值上限",
                    "20%生命值上限",
                    "20%生命值上限",
                    "20%生命值上限",
                    "20%生命值上限",
                    "20%生命值上限",
                    "20%生命值上限",
                    "20%生命值上限",
                    "20%生命值上限"
                ],
                "怪笑猫猫帽继承生命": [
                    "64%",
                    "68.8%",
                    "73.6%",
                    "80%",
                    "84.8%",
                    "89.6%",
                    "96%",
                    "102.4%",
                    "108.8%",
                    "115.2%",
                    "121.6%",
                    "128%",
                    "136%",
                    "144%",
                    "152%"
                ],
                "怪笑猫猫帽持续时间": [
                    "4秒",
                    "4秒",
                    "4秒",
                    "4秒",
                    "4秒",
                    "4秒",
                    "4秒",
                    "4秒",
                    "4秒",
                    "4秒",
                    "4秒",
                    "4秒",
                    "4秒",
                    "4秒",
                    "4秒"
                ],
                "礼花术弹伤害": [
                    "212%",
                    "227.9%",
                    "243.8%",
                    "265%",
                    "280.9%",
                    "296.8%",
                    "318%",
                    "339.2%",
                    "360.4%",
                    "381.6%",
                    "402.8%",
                    "424%",
                    "450.5%",
                    "477%",
                    "503.5%"
                ],
                "灵息之刺伤害": [
                    "27.55%",
                    "29.62%",
                    "31.68%",
                    "34.44%",
                    "36.51%",
                    "38.57%",
                    "41.33%",
                    "44.08%",
                    "46.84%",
                    "49.59%",
                    "52.35%",
                    "55.1%",
                    "58.55%",
                    "61.99%",
                    "65.44%"
                ],
                "灵息之刺间隔": [
                    "6秒",
                    "6秒",
                    "6秒",
                    "6秒",
                    "6秒",
                    "6秒",
                    "6秒",
                    "6秒",
                    "6秒",
                    "6秒",
                    "6秒",
                    "6秒",
                    "6秒",
                    "6秒",
                    "6秒"
                ]
            },
            "description": "<color=#FFD780FF>普通攻击</color>\\n进行至多四段的连续弓箭射击。\\n\\n<color=#FFD780FF>下落攻击</color>\\n从空中射出箭雨，并迅速下坠冲击地面，在落地时造成范围伤害。\\n\\n<color=#FFD780FF>重击</color>\\n进行伤害更高、更为精准的<color=#FFD780FF>瞄准射击</color>。\\n瞄准时，火焰的力量会在箭矢上持续积聚，并随攻击发射出去。根据蓄力时间长短，能造成不同的效果：\\n·一段蓄力：射出附有火元素的箭矢，造成<color=#FF9999FF>火元素伤害</color>；\\n·二段蓄力：发射隐具魔术箭，造成<color=#FF9999FF>火元素伤害</color>，并在命中后，召唤一顶「怪笑猫猫帽」。\\n发射隐具魔术箭时，当林尼的生命值高于60%时，林尼将消耗一部分生命值，并获得一层「隐具余数」，该效果至多叠加5层，会在脱离战斗30秒后清除。\\n通过这种方式，至多使林尼的生命值降低至60%。\\n\\n<color=#FFD780FF>怪笑猫猫帽</color>\\n·能够嘲讽周围的敌人，吸引敌人攻击。每名敌人每5秒只能被怪笑猫猫帽嘲讽一次；\\n·耐久度按比例继承林尼的生命值上限；\\n·被摧毁或持续时间结束时，会对周围的一名敌人发射<color=#FFD780FF>礼花术弹</color>，造成<color=#FF9999FF>火元素伤害</color>。\\n至多同时存在1顶怪笑猫猫帽。\\n\\n<color=#FFD780FF>始基力：芒性</color>\\n每隔一段时间，隐具魔术箭将在命中的位置降下灵息之刺，造成具有芒性的<color=#FF9999FF>火元素伤害</color>。"
        },
        "elementalskill": {
            "name": "眩惑光戏法",
            "icon": "Skill_S_Liney_01",
            "multipliers": {
                "技能伤害": [
                    "167.2%",
                    "179.74%",
                    "192.28%",
                    "209%",
                    "221.54%",
                    "234.08%",
                    "250.8%",
                    "267.52%",
                    "284.24%",
                    "300.96%",
                    "317.68%",
                    "334.4%",
                    "355.3%",
                    "376.2%",
                    "397.1%"
                ],
                "技能伤害加成": [
                    "53.2%攻击力/层",
                    "57.19%攻击力/层",
                    "61.18%攻击力/层",
                    "66.5%攻击力/层",
                    "70.49%攻击力/层",
                    "74.48%攻击力/层",
                    "79.8%攻击力/层",
                    "85.12%攻击力/层",
                    "90.44%攻击力/层",
                    "95.76%攻击力/层",
                    "101.08%攻击力/层",
                    "106.4%攻击力/层",
                    "113.05%攻击力/层",
                    "119.7%攻击力/层",
                    "126.35%攻击力/层"
                ],
                "恢复生命值": [
                    "20%/层",
                    "20%/层",
                    "20%/层",
                    "20%/层",
                    "20%/层",
                    "20%/层",
                    "20%/层",
                    "20%/层",
                    "20%/层",
                    "20%/层",
                    "20%/层",
                    "20%/层",
                    "20%/层",
                    "20%/层",
                    "20%/层"
                ],
                "冷却时间": [
                    "15秒",
                    "15秒",
                    "15秒",
                    "15秒",
                    "15秒",
                    "15秒",
                    "15秒",
                    "15秒",
                    "15秒",
                    "15秒",
                    "15秒",
                    "15秒",
                    "15秒",
                    "15秒",
                    "15秒"
                ]
            },
            "description": "林尼挥动礼帽，引爆惊喜的礼花。\\n施放时，将清除已有的「隐具余数」，对前方的敌人造成<color=#FF9999FF>火元素范围伤害</color>。根据清除的层数，提升造成的伤害，并基于林尼的生命值上限为林尼恢复生命值。\\n\\n场上存在林尼自己创造的怪笑猫猫帽时，礼花将使其猛烈爆炸，造成等同于礼花术弹伤害的<color=#FF9999FF>火元素范围伤害</color>。\\n通过这种方式引爆怪笑猫猫帽造成的伤害视为重击伤害。\\n\\n<i>「众所周知，魔术师经常用的手法就是故意引导观众的注意力…对，在你看向这边的同时，那边的帽子和助手就都不见了，怎么样，很有趣吧。」</i>"
        },
        "elementalburst": {
            "name": "大魔术·灵迹巡游",
            "icon": "Skill_E_Liney_01",
            "multipliers": {
                "技能伤害": [
                    "154%",
                    "165.55%",
                    "177.1%",
                    "192.5%",
                    "204.05%",
                    "215.6%",
                    "231%",
                    "246.4%",
                    "261.8%",
                    "277.2%",
                    "292.6%",
                    "308%",
                    "327.25%",
                    "346.5%",
                    "365.75%"
                ],
                "引爆礼花伤害": [
                    "414%",
                    "445.05%",
                    "476.1%",
                    "517.5%",
                    "548.55%",
                    "579.6%",
                    "621%",
                    "662.4%",
                    "703.8%",
                    "745.2%",
                    "786.6%",
                    "828%",
                    "879.75%",
                    "931.5%",
                    "983.25%"
                ],
                "持续时间": [
                    "3秒",
                    "3秒",
                    "3秒",
                    "3秒",
                    "3秒",
                    "3秒",
                    "3秒",
                    "3秒",
                    "3秒",
                    "3秒",
                    "3秒",
                    "3秒",
                    "3秒",
                    "3秒",
                    "3秒"
                ],
                "冷却时间": [
                    "15秒",
                    "15秒",
                    "15秒",
                    "15秒",
                    "15秒",
                    "15秒",
                    "15秒",
                    "15秒",
                    "15秒",
                    "15秒",
                    "15秒",
                    "15秒",
                    "15秒",
                    "15秒",
                    "15秒"
                ],
                "元素能量": [
                    "60",
                    "60",
                    "60",
                    "60",
                    "60",
                    "60",
                    "60",
                    "60",
                    "60",
                    "60",
                    "60",
                    "60",
                    "60",
                    "60",
                    "60"
                ]
            },
            "description": "林尼施展魔术，化形为能够快速移动的「怪笑帽帽猫」。（并不是「怪笑猫猫帽」。这是两个不同的演出道具！）\\n怪笑帽帽猫接近敌人时，会对身边的敌人降下焰火，对每个敌人造成至多一次<color=#FF9999FF>火元素伤害</color>。持续时间结束时林尼将解除怪笑帽帽猫，引爆华丽的礼花，造成<color=#FF9999FF>火元素范围伤害</color>，召唤一顶怪笑猫猫帽，并获得一层「隐具余数」。\\n\\n可以主动解除怪笑帽帽猫。\\n\\n<i>「那就让你们稍微见识一下吧，要看仔细咯，这是仅属于我们的，独一无二的，奇迹时刻！」</i>"
        },
        "leveling": {
            "crown": {
                "104319": 3
            },
            "books": {
                "104338": 9,
                "104339": 63,
                "104340": 114
            },
            "worldmonster": {
                "112032": 18,
                "112033": 66,
                "112034": 93
            },
            "weekly": {
                "113047": 18
            }
        }
    },
    "passives": {
        "p1": {
            "name": "惊险演出",
            "description": "如果林尼通过发射<color=#FFD780FF>隐具魔术箭</color>消耗了生命值，该隐具魔术箭召唤的怪笑猫猫帽命中敌人时会为林尼恢复3点元素能量，并且基于攻击力的80%提高造成的伤害。",
            "icon": "UI_Talent_S_Liney_05"
        },
        "p2": {
            "name": "完场喝彩",
            "description": "林尼对处于<color=#FF9999FF>火元素</color>影响下的敌人造成的伤害，将以以下方式提升：\\n·基础提升60%；\\n·队伍中林尼以外每个元素类型为<color=#FF9999FF>火元素</color>的角色，提升20%。\\n通过上述方式，至多使林尼对处于<color=#FF9999FF>火元素</color>影响下的敌人造成的伤害提升100%。",
            "icon": "UI_Talent_S_Liney_06"
        },
        "p3": {
            "name": "琐碎观察术",
            "description": "在小地图上显示周围的<color=#FFD780FF>枫丹区域特产</color>的位置。",
            "icon": "UI_Talent_S_Liney_07"
        },
        "p4": ""
    },
    "constellations": {
        "const1": {
            "name": "空取奇思的手艺",
            "description": "<color=#FFD780FF>怪笑猫猫帽</color>至多可以同时存在2顶。\\n此外，隐具魔术箭将在命中时召唤2顶怪笑猫猫帽，并额外积累1层「隐具余数」，该效果每15秒至多触发一次。",
            "icon": "UI_Talent_S_Liney_01"
        },
        "const2": {
            "name": "巧言贴耳的诱引",
            "description": "林尼在场上时，每2秒将获得一层「集意专注」效果，使林尼的暴击伤害提升20%。此效果至多叠加3层，将在林尼退场时解除。",
            "icon": "UI_Talent_S_Liney_03"
        },
        "const3": {
            "name": "玄迷灵敏的指法",
            "description": "<color=#FFD780FF>普通攻击·迫牌易位式</color>的技能等级提高3级。\\n至多提升至15级。",
            "icon": "UI_Talent_U_Liney_01"
        },
        "const4": {
            "name": "熟稔习练的筹谋",
            "description": "林尼的元素类型为<color=#FF9999FF>火元素</color>的重击攻击命中敌人后，该敌人的<color=#FF9999FF>火元素抗性</color>降低20%，持续6秒。",
            "icon": "UI_Talent_S_Liney_02"
        },
        "const5": {
            "name": "穿越隐秘的通术",
            "description": "<color=#FFD780FF>大魔术·灵迹巡游</color>的技能等级提高3级。\\n至多提升至15级。",
            "icon": "UI_Talent_U_Liney_02"
        },
        "const6": {
            "name": "违心的笑",
            "description": "林尼发射<color=#FFD780FF>隐具魔术箭</color>时，将发射一枚礼花术弹·重奏，造成礼花术弹80%的伤害。该伤害视为重击伤害。",
            "icon": "UI_Talent_S_Liney_04"
        }
    },
    "energy": [
        {
            "source": "DropBall_Base",
            "particles": "5",
            "chance": "100%",
            "cd": "0.3s"
        }
    ],
    "attacks": [
        {
            "name": "ShootArrow_Enchanted_WithoutFire",
            "icd_source": "Tag: ExtraAttack (!)",
            "icd_rule": "Independent",
            "gauge": "4U",
            "poise": "LV2/10",
            "element": "-"
        },
        {
            "name": "Bullet_ShootArrow_WithFire",
            "icd_source": "Tag: ExtraAttack (!)",
            "icd_rule": "Independent",
            "gauge": "1U",
            "poise": "LV2/20",
            "element": "Fire"
        },
        {
            "name": "Bullet_ShootArrow_WithFire_BeforeFission",
            "icd_source": "Tag: ExtraAttack (!)",
            "icd_rule": "Independent",
            "gauge": "1U",
            "poise": "LV2/30",
            "element": "Fire"
        },
        {
            "name": "Bullet_ShootArrow_WithFire_BeforeFission",
            "icd_source": "Tag: ExtraAttack (!)",
            "icd_rule": "Independent",
            "gauge": "1U",
            "poise": "LV2/30",
            "element": "Fire"
        },
        {
            "name": "SkillObj_ShootArrow_OusiaAgent",
            "icd_source": "Tag: ExtraAttack (!)",
            "icd_rule": "Independent",
            "gauge": "0U",
            "poise": "LV2/20",
            "element": "Fire"
        },
        {
            "name": "Bullet_FissionAgent_EndBoom",
            "icd_source": "Grp: Avatar_Liney_ExtraAttack (Tag Miss)",
            "icd_rule": "6 hits / 1s",
            "gauge": "1U",
            "poise": "LV2/30",
            "element": "Fire"
        },
        {
            "name": "Bullet_FissionAgent_EndBoom_Constellation_6",
            "icd_source": "Grp: Avatar_Liney_ExtraAttack (Tag Miss)",
            "icd_rule": "6 hits / 1s",
            "gauge": "1U",
            "poise": "LV2/30",
            "element": "Fire"
        },
        {
            "name": "SkillObj_FissionAgent_EndBoom_Enhanced",
            "icd_source": "Grp: Avatar_Liney_ExtraAttack (Tag Miss)",
            "icd_rule": "6 hits / 1s",
            "gauge": "1U",
            "poise": "LV2/90",
            "element": "Fire"
        },
        {
            "name": "ElementalArt",
            "icd_source": "Tag: Elemental_Art (!)",
            "icd_rule": "Independent",
            "gauge": "1U",
            "poise": "LV4/60",
            "element": "Fire"
        },
        {
            "name": "ElementalBurst",
            "icd_source": "Tag: Elemental_Burst (!)",
            "icd_rule": "Independent",
            "gauge": "1U",
            "poise": "LV2/40",
            "element": "Fire"
        },
        {
            "name": "ElementalBurst",
            "icd_source": "Tag: Elemental_Burst (!)",
            "icd_rule": "Independent",
            "gauge": "1U",
            "poise": "LV7/120",
            "element": "Fire"
        },
        {
            "name": "FallingAnthem",
            "icd_source": "Tag: FallingAttack (!)",
            "icd_rule": "Independent",
            "gauge": "0U",
            "poise": "LV2/10",
            "element": "-"
        },
        {
            "name": "FallingAnthem",
            "icd_source": "Tag: FallingAttack (!)",
            "icd_rule": "Independent",
            "gauge": "1U",
            "poise": "LV2/50",
            "element": "-"
        },
        {
            "name": "FallingAnthem",
            "icd_source": "Tag: FallingAttack (!)",
            "icd_rule": "Independent",
            "gauge": "1U",
            "poise": "LV3/100",
            "element": "-"
        }
    ],
    "hyperlinks": []
}
